QmlbookZhongwenban/README.md
QmlbookZhongwenban/__init__.py
QmlbookZhongwenban/__main__.py
QmlbookZhongwenban/file.epub
QmlbookZhongwenban/index.html
QmlbookZhongwenban/css/__init__.py
QmlbookZhongwenban/css/annotations.css
QmlbookZhongwenban/css/main.css
QmlbookZhongwenban/css/normalize.css
QmlbookZhongwenban/css/popup.css
QmlbookZhongwenban/font/__init__.py
QmlbookZhongwenban/font/fontello.eot
QmlbookZhongwenban/font/fontello.svg
QmlbookZhongwenban/font/fontello.ttf
QmlbookZhongwenban/font/fontello.woff
QmlbookZhongwenban/img/__init__.py
QmlbookZhongwenban/img/annotator-glyph-sprite.png
QmlbookZhongwenban/img/annotator-icon-sprite.png
QmlbookZhongwenban/img/apple-touch-icon.png
QmlbookZhongwenban/img/cancelfullscreen.png
QmlbookZhongwenban/img/close.png
QmlbookZhongwenban/img/fullscreen.png
QmlbookZhongwenban/img/loader.gif
QmlbookZhongwenban/img/menu-icon.png
QmlbookZhongwenban/img/save.png
QmlbookZhongwenban/img/saved.png
QmlbookZhongwenban/img/settings-s.png
QmlbookZhongwenban/img/settings.png
QmlbookZhongwenban/img/star.png
QmlbookZhongwenban/js/__init__.py
QmlbookZhongwenban/js/epub.js
QmlbookZhongwenban/js/epub.min.js
QmlbookZhongwenban/js/epub.min.map
QmlbookZhongwenban/js/hooks.min.js
QmlbookZhongwenban/js/hooks.min.map
QmlbookZhongwenban/js/reader.js
QmlbookZhongwenban/js/reader.js.map
QmlbookZhongwenban/js/reader.min.js
QmlbookZhongwenban/js/reader.min.map
QmlbookZhongwenban/js/hooks/__init__.py
QmlbookZhongwenban/js/hooks/extensions/__init__.py
QmlbookZhongwenban/js/hooks/extensions/highlight.js
QmlbookZhongwenban/js/libs/__init__.py
QmlbookZhongwenban/js/libs/jquery.min.js
QmlbookZhongwenban/js/libs/localforage.min.js
QmlbookZhongwenban/js/libs/screenfull.js
QmlbookZhongwenban/js/libs/screenfull.min.js
QmlbookZhongwenban/js/libs/zip.min.js
QmlbookZhongwenban/js/plugins/__init__.py
QmlbookZhongwenban/js/plugins/hypothesis.js
QmlbookZhongwenban/js/plugins/search.js
qmlbook_zhongwenban-2024.3.2.0.dist-info/METADATA
qmlbook_zhongwenban-2024.3.2.0.dist-info/WHEEL
qmlbook_zhongwenban-2024.3.2.0.dist-info/entry_points.txt
qmlbook_zhongwenban-2024.3.2.0.dist-info/top_level.txt
qmlbook_zhongwenban-2024.3.2.0.dist-info/RECORD
